ml_eval_dashboard/__init__.py
ml_eval_dashboard/dashboard.py
ml_eval_dashboard/evaluator.py
ml_eval_dashboard/main.py
ml_eval_dashboard/report_generator.py
ml_eval_dashboard/visualizer.py
ml_eval_dashboard-0.1.1.dist-info/LICENCE
ml_eval_dashboard-0.1.1.dist-info/METADATA
ml_eval_dashboard-0.1.1.dist-info/WHEEL
ml_eval_dashboard-0.1.1.dist-info/entry_points.txt
ml_eval_dashboard-0.1.1.dist-info/top_level.txt
ml_eval_dashboard-0.1.1.dist-info/RECORD
