Metadata-Version: 2.1
Name: ml-eval-dashboard
Version: 0.1.1
Summary: Reusable ML Evaluation Dashboard built with Streamlit
Home-page: UNKNOWN
Author: Your Name
Author-email: your.email@example.com
License: UNKNOWN
Platform: UNKNOWN
License-File: LICENCE
Requires-Dist: streamlit
Requires-Dist: pandas
Requires-Dist: plotly
Requires-Dist: fpdf
Requires-Dist: numpy
Requires-Dist: matplotlib
Requires-Dist: seaborn
Requires-Dist: scikit-learn
